{
  "query": [
    {
      "code": "Rakennusvaihe",
      "selection": {
        "filter": "item",
        "values": [
          "2",
          "3"
        ]
      }
    },
    {
      "code": "Alue",
      "selection": {
        "filter": "item",
        "values": [
          "SSS"
        ]
      }
    },
    {
      "code": "Käyttötarkoitus",
      "selection": {
        "filter": "item",
        "values": [
          "SSS",
          "01",
          "011",
          "012",
          "013",
          "014",
          "02T19",
          "02",
          "03T05",
          "03",
          "04",
          "05",
          "06T08_13",
          "06",
          "07",
          "08",
          "09T12",
          "09",
          "10",
          "11",
          "12",
          "13",
          "14",
          "19"
        ]
      }
    },
    {
      "code": "Tiedot",
      "selection": {
        "filter": "item",
        "values": [
          "kerrosala",
          "asuntolkm"
        ]
      }
    }
  ],
  "response": {
    "format": "json"
  }
}